pl_tmobile_sms_gateway/__init__.py
pl_tmobile_sms_gateway/__version__.py
pl_tmobile_sms_gateway/base.py
pl_tmobile_sms_gateway/exceptions.py
pl_tmobile_sms_gateway/models.py
pl_tmobile_sms_gateway/tmobile.py
pl_tmobile_sms_gateway-0.1.1.dist-info/LICENSE
pl_tmobile_sms_gateway-0.1.1.dist-info/METADATA
pl_tmobile_sms_gateway-0.1.1.dist-info/WHEEL
pl_tmobile_sms_gateway-0.1.1.dist-info/top_level.txt
pl_tmobile_sms_gateway-0.1.1.dist-info/RECORD
