Metadata-Version: 2.1
Name: pl-tmobile-sms-gateway
Version: 0.1.1
Summary: Dead simple wrapper for T-Mobile Poland SMS gateway
Home-page: https://github.com/krzysztofmo/pl_tmobile_sms_gateway
Author: Krzysztof Mochejski
License: UNKNOWN
Platform: UNKNOWN
Classifier: Programming Language :: Python :: 3
Classifier: License :: OSI Approved :: GNU General Public License v2 (GPLv2)
Classifier: Operating System :: OS Independent
